mplotutils/__init__.py
mplotutils/_cartopy_utils.py
mplotutils/_colorbar.py
mplotutils/_colormaps.py
mplotutils/_deprecate.py
mplotutils/_hatch.py
mplotutils/_map_layout.py
mplotutils/_mpl.py
mplotutils/_savefig.py
mplotutils/_xrcompat.py
mplotutils/cartopy_utils.py
mplotutils/colormaps.py
mplotutils/map_layout.py
mplotutils/mpl.py
mplotutils/xrcompat.py
mplotutils/tests/__init__.py
mplotutils/tests/conftest.py
mplotutils/tests/test_colorbar.py
mplotutils/tests/test_colormap.py
mplotutils/tests/test_cyclic_dataarray.py
mplotutils/tests/test_deprecate.py
mplotutils/tests/test_get_renderer.py
mplotutils/tests/test_hatch.py
mplotutils/tests/test_infer_interval_breaks.py
mplotutils/tests/test_label_map.py
mplotutils/tests/test_mapticklabels.py
mplotutils/tests/test_maybe_gca.py
mplotutils/tests/test_rename_modules.py
mplotutils/tests/test_sample_data_map.py
mplotutils/tests/test_savefig.py
mplotutils/tests/test_set_map_layout.py
mplotutils/tests/test_set_map_layout_axes_grid.py
mplotutils-0.6.0.dist-info/LICENSE
mplotutils-0.6.0.dist-info/METADATA
mplotutils-0.6.0.dist-info/WHEEL
mplotutils-0.6.0.dist-info/top_level.txt
mplotutils-0.6.0.dist-info/RECORD
