Metadata-Version: 2.1
Name: mplotutils
Version: 0.6.0
Summary: utilities for matplotlib and cartopy
Home-page: https://github.com/mpytools/mplotutils
Author: mathause
Author-email: mathias.hauser@env.ethz.com
License: GPLv3
Classifier: Development Status :: 4 - Beta
Classifier: License :: OSI Approved :: MIT License
Classifier: Operating System :: OS Independent
Classifier: Intended Audience :: Science/Research
Classifier: Programming Language :: Python
Classifier: Programming Language :: Python :: 3
Classifier: Programming Language :: Python :: 3.10
Classifier: Programming Language :: Python :: 3.11
Classifier: Programming Language :: Python :: 3.12
Requires-Python: >=3.10
License-File: LICENSE
Requires-Dist: cartopy>=0.22
Requires-Dist: matplotlib>=3.8
Requires-Dist: numpy>=1.24
Requires-Dist: xarray>=2023.9
